git_browse_remote/__init__.py
git_browse_remote/cmd.py
git_browse_remote/logger.py
git_browse_remote/main.py
git_browse_remote/test/__init__.py
git_browse_remote/test/test_main.py
git_browse_remote-0.1.3.dist-info/LICENSE
git_browse_remote-0.1.3.dist-info/METADATA
git_browse_remote-0.1.3.dist-info/WHEEL
git_browse_remote-0.1.3.dist-info/entry_points.txt
git_browse_remote-0.1.3.dist-info/RECORD
