Metadata-Version: 2.1
Name: git-browse-remote
Version: 0.1.3
Summary: Browse the GitHub repository with the browser
License: CC0-1.0
Author: nonylene
Author-email: nonylene@gmail.com
Requires-Python: >=3.11,<4.0
Classifier: License :: CC0 1.0 Universal (CC0 1.0) Public Domain Dedication
Classifier: Programming Language :: Python :: 3
Classifier: Programming Language :: Python :: 3.11
Classifier: Programming Language :: Python :: 3.12
Requires-Dist: click (>=8.1.7,<9.0.0)
Requires-Dist: pygit2 (>=1.15.1,<2.0.0)
